fleaky/__init__.py
fleaky/geom.py
fleaky/py.typed
fleaky-0.0.1.dist-info/LICENSE
fleaky-0.0.1.dist-info/METADATA
fleaky-0.0.1.dist-info/WHEEL
fleaky-0.0.1.dist-info/RECORD
