Metadata-Version: 2.1
Name: fleaky
Version: 0.0.1
Summary: Fleaky
Home-page: https://github.com/benvial/fleaky
License: GPL-3.0
Author: Benjamin Vial
Author-email: contact@bvial.info
Requires-Python: >=3.9,<4.0
Classifier: Development Status :: 3 - Alpha
Classifier: License :: OSI Approved :: GNU General Public License v3 (GPLv3)
Classifier: Programming Language :: Python :: 3
Classifier: Programming Language :: Python :: 3.9
Classifier: Programming Language :: Python :: 3.10
Classifier: Programming Language :: Python :: 3.11
Classifier: Programming Language :: Python :: 3.12
Requires-Dist: dmsuite (==0.3.0)
Requires-Dist: flake8 (>=7.1.0,<8.0.0)
Requires-Dist: poetry-plugin-export (>=1.8.0,<2.0.0)
Project-URL: Changelog, https://github.com/benvial/fleaky/releases
Project-URL: Documentation, https://fleaky.readthedocs.io
Project-URL: Repository, https://github.com/benvial/fleaky
